LICENSE
MANIFEST.in
README.rst
setup.py
django_subdomains_handler.egg-info/PKG-INFO
django_subdomains_handler.egg-info/SOURCES.txt
django_subdomains_handler.egg-info/dependency_links.txt
django_subdomains_handler.egg-info/top_level.txt
lightsub/__init__.py
lightsub/middleware.py